payslip_parser/__init__.py
payslip_parser/configuration/__init__.py
payslip_parser/configuration/config.py
payslip_parser/configuration/idf_payslip_config.yaml
payslip_parser/configuration/loader.py
payslip_parser/parsers/__init__.py
payslip_parser/parsers/base_payslip_parser.py
payslip_parser/parsers/idf_payslip_parser.py
payslip_parser/parsers/payslip_directory_parser.py
payslip_parser/payslips/__init__.py
payslip_parser/payslips/payslip.py
payslip_parser/text_blocks/__init__.py
payslip_parser/text_blocks/base_text_block.py
payslip_parser/text_blocks/idf_text_block.py
payslip_parser/utils/__init__.py
payslip_parser/utils/consts.py
payslip_parser-0.1.4.dist-info/METADATA
payslip_parser-0.1.4.dist-info/WHEEL
payslip_parser-0.1.4.dist-info/RECORD
